xword_dl/__init__.py
xword_dl/__main__.py
xword_dl/_version.py
xword_dl/xword_dl.py
xword_dl/downloader/__init__.py
xword_dl/downloader/amuniversaldownloader.py
xword_dl/downloader/amuselabsdownloader.py
xword_dl/downloader/atlanticdownloader.py
xword_dl/downloader/basedownloader.py
xword_dl/downloader/compilerdownloader.py
xword_dl/downloader/crosswordclubdownloader.py
xword_dl/downloader/dailybeastdownloader.py
xword_dl/downloader/dailypopdownloader.py
xword_dl/downloader/derstandarddownloader.py
xword_dl/downloader/globeandmaildownloader.py
xword_dl/downloader/guardiandownloader.py
xword_dl/downloader/latimesdownloader.py
xword_dl/downloader/mckinseydownloader.py
xword_dl/downloader/newsdaydownloader.py
xword_dl/downloader/newyorkerdownloader.py
xword_dl/downloader/newyorktimesdownloader.py
xword_dl/downloader/observerdownloader.py
xword_dl/downloader/puzzlesocietydownloader.py
xword_dl/downloader/puzzmodownloader.py
xword_dl/downloader/simplydailydownloader.py
xword_dl/downloader/voxdownloader.py
xword_dl/downloader/walrusdownloader.py
xword_dl/downloader/wapodownloader.py
xword_dl/downloader/wsjdownloader.py
xword_dl/util/__init__.py
xword_dl/util/utils.py
xword_dl-2025.10.3.dist-info/METADATA
xword_dl-2025.10.3.dist-info/WHEEL
xword_dl-2025.10.3.dist-info/entry_points.txt
xword_dl-2025.10.3.dist-info/licenses/LICENSE
xword_dl-2025.10.3.dist-info/RECORD
