Metadata-Version: 2.4
Name: xword-dl
Version: 2025.10.3
Summary: CLI download tool for online crossword puzzles
Author-email: Parker Higgins <parker@parkerhiggins.net>
License-Expression: MIT
License-File: LICENSE
Requires-Python: >=3.10
Requires-Dist: beautifulsoup4==4.13.4
Requires-Dist: dateparser==1.2.2
Requires-Dist: emoji==2.14.1
Requires-Dist: html2text==2025.4.15
Requires-Dist: lxml==6.0.0
Requires-Dist: puzpy==0.2.6
Requires-Dist: pyyaml==6.0.2
Requires-Dist: requests==2.32.4
Requires-Dist: unidecode==1.4.0
Requires-Dist: xmltodict==0.14.2
